dcggraph/__init__.py
dcggraph/search.py
dcggraph-0.0.9.dist-info/LICENSE
dcggraph-0.0.9.dist-info/METADATA
dcggraph-0.0.9.dist-info/WHEEL
dcggraph-0.0.9.dist-info/top_level.txt
dcggraph-0.0.9.dist-info/RECORD
