Metadata-Version: 2.1
Name: dcggraph
Version: 0.0.9
Summary: Directed Cyclic Graph Utilities for Python
Home-page: https://github.com/ssteffl/python-dcggraph
Author: Sam Steffl
Author-email: sam@ssteffl.com
License: UNKNOWN
Project-URL: Bug Reports, https://github.com/ssteffl/python-dcggraph
Project-URL: Source, https://github.com/ssteffl/python-dcggraph
Keywords: directed cyclic graph traversal
Platform: UNKNOWN
Classifier: Development Status :: 3 - Alpha
Classifier: Intended Audience :: Developers
Classifier: Topic :: Software Development :: Libraries
Classifier: License :: OSI Approved :: MIT License
Classifier: Programming Language :: Python :: 3
Requires-Python: >=3.6
Requires-Dist: typing
